test.py
Tool/__init__.py
Tool/tool.py
song_toollib2-1.0.0.dist-info/LICENSE.txt
song_toollib2-1.0.0.dist-info/METADATA
song_toollib2-1.0.0.dist-info/WHEEL
song_toollib2-1.0.0.dist-info/top_level.txt
song_toollib2-1.0.0.dist-info/RECORD
