Metadata-Version: 2.1
Name: song-toollib2
Version: 1.0.0
Summary: this is a xxx lib
Home-page: http://www.baidu.com
Author: songzixue
Author-email: 10806186@qq.com
License: UNKNOWN
Platform: UNKNOWN
